modelmatcher/__init__.py
modelmatcher/model_io.py
modelmatcher/models.py
modelmatcher/version.py
modelmatcher-1.2.data/scripts/modelmatcher
tests/__init__.py
tests/models_test.py
modelmatcher-1.2.dist-info/METADATA
modelmatcher-1.2.dist-info/WHEEL
modelmatcher-1.2.dist-info/top_level.txt
modelmatcher-1.2.dist-info/RECORD
