Metadata-Version: 2.1
Name: modelmatcher
Version: 1.2
Summary: Rapid identification of sequence evolution models
Home-page: https://github.com/arvestad/modelmatcher
Author: Lars Arvestad
Author-email: arve@math.su.se
License: UNKNOWN
Platform: UNKNOWN
Classifier: Programming Language :: Python :: 3
Classifier: License :: OSI Approved :: GNU General Public License v3 (GPLv3)
Classifier: Operating System :: OS Independent
Classifier: Topic :: Scientific/Engineering :: Bio-Informatics
Requires-Python: >=3.2
Requires-Dist: biopython (>=1.70)
Requires-Dist: numpy
Requires-Dist: console-progressbar (>=1.1.2)
